{
    "entities": [
        {
            "name": "ActionPrefab",
            "tags": [
                "flecs.core.Prefab",
                "Action"
            ]
        },
        {
            "name": "ActionCreate",
            "tags": [
                "flecs.core.Prefab"
            ],
            "pairs": {
                "LoadMode": "LoadMode.Create",
                "flecs.core.IsA": "ActionPrefab"
            }
        },
        {
            "name": "ActionEdit",
            "tags": [
                "flecs.core.Prefab"
            ],
            "pairs": {
                "LoadMode": "LoadMode.Edit",
                "flecs.core.IsA": "ActionPrefab"
            }
        },
        {
            "name": "ActionDestroy",
            "tags": [
                "flecs.core.Prefab"
            ],
            "pairs": {
                "LoadMode": "LoadMode.Destroy",
                "flecs.core.IsA": "ActionPrefab"
            }
        },
        {
            "name": "Local",
            "tags": [
                "flecs.core.Prefab"
            ],
            "components": {
                "Parent": {
                    "Value": ""
                }
            }
        },
        {
            "name": "ActionNormalBoxRoundedOutlined",
            "tags": [
                "flecs.core.Prefab"
            ],
            "pairs": {
                "Event": "Event.Normal",
                "flecs.core.IsA": [
                    "ActionEdit",
                    "Local"
                ]
            },
            "components": {
                "Path": {
                    "Value": "UI/Actions/NormalBoxRoundedOutlined"
                }
            }
        },
        {
            "name": "ActionHoveredBoxRoundedOutlined",
            "tags": [
                "flecs.core.Prefab"
            ],
            "pairs": {
                "Event": "Event.Hovered",
                "flecs.core.IsA": [
                    "ActionEdit",
                    "Local"
                ]
            },
            "components": {
                "Path": {
                    "Value": "UI/Actions/HoveredBoxRoundedOutlined"
                }
            }
        },
        {
            "name": "ActionPressedBoxRoundedOutlined",
            "tags": [
                "flecs.core.Prefab"
            ],
            "pairs": {
                "Event": "Event.Pressed",
                "flecs.core.IsA": [
                    "ActionEdit",
                    "Local"
                ]
            },
            "components": {
                "Path": {
                    "Value": "UI/Actions/PressedBoxRoundedOutlined"
                }
            }
        }
    ]
}